glap_model/__init__.py
glap_model/config.py
glap_model/dataset.py
glap_model/inference.py
glap_model/metrics.py
glap_model/torchtyping.py
glap_model/trainer.py
glap_model/grad_cache/__init__.py
glap_model/grad_cache/context_managers.py
glap_model/grad_cache/functional.py
glap_model/grad_cache/grad_cache.py
glap_model/grad_cache/loss.py
glap_model/grad_cache/cachex/__init__.py
glap_model/grad_cache/cachex/functional.py
glap_model/grad_cache/cachex/training.py
glap_model/grad_cache/cachex/tree_utils.py
glap_model/grad_cache/pytorch_lightning/pl_example.py
glap_model/grad_cache/pytorch_lightning/pl_gradcache.py
glap_model/grad_cache/pytorch_lightning/readme.md
glap_model/grad_cache/pytorch_lightning/requirements.txt
glap_model/models/__init__.py
glap_model/models/glap.py
glap_model/models/losses.py
glap_model/models/audioencoders/__init__.py
glap_model/models/audioencoders/beats_wrapper.py
glap_model/models/audioencoders/dasheng_audioencoder.py
glap_model/models/audioencoders/wavlm_wrapper.py
glap_model/models/audioencoders/whisper_wrapper.py
glap_model/models/audioencoders/beats/BEATs.py
glap_model/models/audioencoders/beats/backbone.py
glap_model/models/audioencoders/beats/beats_models.py
glap_model/models/audioencoders/beats/modules.py
glap_model/models/textencoders/__init__.py
glap_model/models/textencoders/bert.py
glap_model/models/textencoders/clip_textencoder.py
glap_model/models/textencoders/deberta.py
glap_model/models/textencoders/flan_t5.py
glap_model/models/textencoders/gpt2.py
glap_model/models/textencoders/gte.py
glap_model/models/textencoders/qwen25.py
glap_model/models/textencoders/scratch.py
glap_model/models/textencoders/sonar_text_encoder.py
glap_model/models/textencoders/xlm_roberta.py
glap_model/pretrained/hf_pretrained.py
glap_model/pretrained/pretrained.py
glap_model-0.0.11.dist-info/METADATA
glap_model-0.0.11.dist-info/WHEEL
glap_model-0.0.11.dist-info/entry_points.txt
glap_model-0.0.11.dist-info/licenses/LICENSE
glap_model-0.0.11.dist-info/RECORD
