Metadata-Version: 2.4
Name: glap-model
Version: 0.0.11
Project-URL: Homepage, https://github.com/xiaomi-research/GLAP
Project-URL: Documentation, https://github.com/xiaomi-research/GLAP
Project-URL: Repository, https://github.com/xiaomi-research/GLAP
Project-URL: Issues, https://github.com/xiaomi-research/GLAP/issues
Author-email: Heinrich Dinkel <dinkelheinrich@xiaomi.com>, Junbo Zhang <zhangjunbo1@xiaomi.com>
Maintainer-email: Heinrich Dinkel <dinkelheinrich@xiaomi.com>, Junbo Zhang <zhangjunbo1@xiaomi.com>
License:                                  Apache License
License-File: LICENSE
Classifier: Development Status :: 3 - Alpha
Classifier: Environment :: GPU :: NVIDIA CUDA :: 11.4
Classifier: Environment :: GPU :: NVIDIA CUDA :: 12
Classifier: Intended Audience :: Developers
Classifier: License :: OSI Approved :: Apache Software License
Classifier: Programming Language :: Python :: 3.10
Classifier: Programming Language :: Python :: 3.11
Classifier: Topic :: Multimedia :: Sound/Audio :: Speech
Classifier: Topic :: Software Development :: Build Tools
Requires-Python: >=3.10
Requires-Dist: dasheng
Requires-Dist: fairseq2>=0.4.5
Requires-Dist: jaxtyping
Requires-Dist: loguru
Requires-Dist: numpy
Requires-Dist: pyyaml
Requires-Dist: sentencepiece
Requires-Dist: setuptools
Requires-Dist: sonar-space
Requires-Dist: soundfile
Requires-Dist: torch>=1.8.2
Requires-Dist: torchaudio
Requires-Dist: torchinfo
Requires-Dist: transformers
Provides-Extra: dev
Requires-Dist: accelerate; extra == 'dev'
Requires-Dist: bitsandbytes; extra == 'dev'
Requires-Dist: einops; extra == 'dev'
Requires-Dist: fire; extra == 'dev'
Requires-Dist: pandas; extra == 'dev'
Requires-Dist: phonemizer; extra == 'dev'
Requires-Dist: pytorch-ignite; extra == 'dev'
Requires-Dist: scipy; extra == 'dev'
Requires-Dist: tokenizers; extra == 'dev'
Requires-Dist: webdataset; extra == 'dev'
